{
  "version": "4.5.5",
  "flags": {},
  "shapes": [
    {
      "label": "joint",
      "points": [
        [
          526.1860465116279,
          522.9069767441861
        ],
        [
          526.1860465116279,
          721.7441860465117
        ],
        [
          1344.7906976744187,
          704.3023255813954
        ],
        [
          1335.4883720930234,
          498.48837209302326
        ]
      ],
      "group_id": null,
      "shape_type": "polygon",
      "flags": {}
    }
  ],
  "imagePath": "1586019696.907211_image_96483.jpg",
  "imageData": null,
  "imageHeight": 1536,
  "imageWidth": 2048
}